MANIFEST.in
README.txt
setup.cfg
setup.py
collective/__init__.py
collective.marshall.workflow.egg-info/PKG-INFO
collective.marshall.workflow.egg-info/SOURCES.txt
collective.marshall.workflow.egg-info/dependency_links.txt
collective.marshall.workflow.egg-info/entry_points.txt
collective.marshall.workflow.egg-info/namespace_packages.txt
collective.marshall.workflow.egg-info/not-zip-safe
collective.marshall.workflow.egg-info/requires.txt
collective.marshall.workflow.egg-info/top_level.txt
collective/marshall/__init__.py
collective/marshall/workflow/__init__.py
collective/marshall/workflow/configure.zcml
collective/marshall/workflow/events.py
collective/marshall/workflow/handlers.py
collective/marshall/workflow/interfaces.py
collective/marshall/workflow/tests.py
collective/marshall/workflow/version.txt
collective/marshall/workflow/namespaces/__init__.py
collective/marshall/workflow/namespaces/workflow.py
docs/HISTORY.txt
docs/INSTALL.txt
docs/LICENSE.GPL
docs/LICENSE.txt