Metadata-Version: 1.0
Name: collective.marshall.workflow
Version: 1.0.3
Summary: A Namespace Extension for ATXML
Home-page: http://www.brainson.de/
Author: Oliver Roch
Author-email: oliver.roch@brainson.de
License: GPL
Platform: UNKNOWN
Classifier: Framework :: Plone
Classifier: Programming Language :: Python
Classifier: Topic :: Software Development :: Libraries :: Python Modules
